vacc/__init__.py
vacc/rsync.py
vacc/submitter.py
vacc-0.1.1.dist-info/LICENSE
vacc-0.1.1.dist-info/METADATA
vacc-0.1.1.dist-info/WHEEL
vacc-0.1.1.dist-info/top_level.txt
vacc-0.1.1.dist-info/RECORD
