Metadata-Version: 2.1
Name: vacc
Version: 0.1.1
Summary: Helper package for running code on UVM's VACC
Home-page: http://github.com/erikweis/vacc
Author: Erik Weis
Author-email: erik.weis@uvm.edu
License: UVM
License-File: LICENSE
